iogp/__init__.py
iogp/data/__init__.py
iogp/data/archive.py
iogp/data/asn1.py
iogp/data/carve.py
iogp/data/dataview.py
iogp/data/ds.py
iogp/data/fileid.py
iogp/data/map437.py
iogp/data/oid.py
iogp/data/str.py
iogp/db/__init__.py
iogp/db/cache.py
iogp/db/dbobj.py
iogp/db/sqlite.py
iogp/gui/__init__.py
iogp/gui/qt.py
iogp/gui/qthexed.py
iogp/gui/qtwidgets.py
iogp/net/__init__.py
iogp/net/net.py
iogp/net/packet.py
iogp/win/__init__.py
iogp/win/win.py
iogp-1.0.9.dist-info/METADATA
iogp-1.0.9.dist-info/WHEEL
iogp-1.0.9.dist-info/licenses/LICENSE
iogp-1.0.9.dist-info/RECORD
