Metadata-Version: 2.3
Name: iogp
Version: 1.0.9
Summary: Python common task, general purpose library (serialization, networking, etc.).
Project-URL: Homepage, https://gitlab.com/vtopan/iogp
Author-email: Vlad Topan <vtopan@gmail.removethispart.com>
License: MIT License
Classifier: License :: OSI Approved :: MIT License
Classifier: Programming Language :: Python
Classifier: Programming Language :: Python :: 3
Requires-Python: >=3.9
